mickelonius/__init__.py
mickelonius/config.py
mickelonius/dataviz/__init__.py
mickelonius/feature_engineering/__init__.py
mickelonius/feature_engineering/woe.py
mickelonius/regression/__init__.py
mickelonius/stat/__init__.py
mickelonius/stat/hypothesis_testing/__init__.py
mickelonius/stat/hypothesis_testing/anova/__init__.py
mickelonius/stat/hypothesis_testing/categorical/__init__.py
mickelonius/stat/hypothesis_testing/continuous/__init__.py
mickelonius/stat/hypothesis_testing/continuous/comparing_means.py
mickelonius/stat/hypothesis_testing/count/__init__.py
mickelonius/stat/hypothesis_testing/count/data/__init__.py
mickelonius/stat/hypothesis_testing/count/data/generate_poisson_data.py
mickelonius/stat/hypothesis_testing/stationarity/__init__.py
mickelonius/stat/hypothesis_testing/stationarity/augmented_dickey_fuller.py
mickelonius/stat/hypothesis_testing/stationarity/phillips_perron.py
mickelonius/time_series/__init__.py
mickelonius/time_series/aggregations.py
mickelonius/time_series/features.py
mickelonius/time_series/frac_diff.py
mickelonius/time_series/labelling.py
mickelonius/time_series/sampling.py
mickelonius/training_validation/__init__.py
mickelonius/training_validation/reusable_holdout/ReusableHoldout.py
mickelonius/training_validation/reusable_holdout/__init__.py
mickelonius/unsupervised/__init__.py
mickelonius/utils/__init__.py
mickelonius/utils/dates.py
mickelonius/utils/units.py
tests/__init__.py
tests/conftest.py
tests/test_aggregation.py
tests/test_labelling.py
tests/test_sampling.py
tests/test_stationarity.py
tests/test_time_series_features.py
tests/test_time_series_fracdiff.py
tests/test_woe_tgt_encode.py
tests/utils.py
mickelonius-0.0.3.dist-info/METADATA
mickelonius-0.0.3.dist-info/WHEEL
mickelonius-0.0.3.dist-info/top_level.txt
mickelonius-0.0.3.dist-info/RECORD
